MANIFEST.in
README.markdown
README.txt
setup.py
./pyramid_selectable_renderer/__init__.py
./pyramid_selectable_renderer/custom.py
./pyramid_selectable_renderer/interfaces.py
./pyramid_selectable_renderer/tests.py
pyramid_selectable_renderer.egg-info/PKG-INFO
pyramid_selectable_renderer.egg-info/SOURCES.txt
pyramid_selectable_renderer.egg-info/dependency_links.txt
pyramid_selectable_renderer.egg-info/entry_points.txt
pyramid_selectable_renderer.egg-info/not-zip-safe
pyramid_selectable_renderer.egg-info/requires.txt
pyramid_selectable_renderer.egg-info/top_level.txt