Metadata-Version: 1.0
Name: pyramid-selectable-renderer
Version: 0.0.2
Summary: using multi template on one view_config
Home-page: https://github.com/podhmo/pyramid_selectable_renderer
Author: podhmo
Author-email: ababjam61@gmail.com
License: UNKNOWN
Platform: UNKNOWN
